README.rst
setup.cfg
setup.py
sequana_coverage.egg-info/PKG-INFO
sequana_coverage.egg-info/SOURCES.txt
sequana_coverage.egg-info/dependency_links.txt
sequana_coverage.egg-info/entry_points.txt
sequana_coverage.egg-info/not-zip-safe
sequana_coverage.egg-info/requires.txt
sequana_coverage.egg-info/top_level.txt
sequana_pipelines/coverage/__init__.py
sequana_pipelines/coverage/config.yaml
sequana_pipelines/coverage/coverage.rules
sequana_pipelines/coverage/main.py
sequana_pipelines/coverage/multiqc_config.yaml
sequana_pipelines/coverage/requirements.txt
sequana_pipelines/coverage/schema.yaml
sequana_pipelines/coverage/data/JB409847.bed
sequana_pipelines/coverage/data/JB409847.fa
sequana_pipelines/coverage/data/JB409847.gbk
sequana_pipelines/coverage/data/JB409847_R1_clean.fastq.gz
sequana_pipelines/coverage/data/JB409847_bis.bed
sequana_pipelines/coverage/data/README.rst
sequana_pipelines/coverage/data/__init__.py
test/test_main.py