Metadata-Version: 1.2
Name: sequana-coverage
Version: 0.9.1
Summary: Parallelise version of sequana_coverage standalone application.
Home-page: https://github.com/sequana/
Author: thomas cokelaer
Author-email: thomas.cokelaer@pasteur.fr
Maintainer: thomas cokelaer
Maintainer-email: thomas.cokelaer@pasteur.fr
License: new BSD
Keywords: coverage, snakemake, sequana, running median, CNV, depltion
Platform: Linux
Platform: Unix
Platform: MacOsX
Platform: Windows
Classifier: Development Status :: 4 - Beta
Classifier: Intended Audience :: Education
Classifier: Intended Audience :: End Users/Desktop
Classifier: Intended Audience :: Developers
Classifier: Intended Audience :: Science/Research
Classifier: License :: OSI Approved :: BSD License
Classifier: Operating System :: OS Independent
Classifier: Programming Language :: Python :: 3.5
Classifier: Programming Language :: Python :: 3.6
Classifier: Topic :: Software Development :: Libraries :: Python Modules
Classifier: Topic :: Scientific/Engineering :: Bio-Informatics
Classifier: Topic :: Scientific/Engineering :: Information Analysis
Classifier: Topic :: Scientific/Engineering :: Mathematics
Classifier: Topic :: Scientific/Engineering :: Physics
